[{"id":0,"href":"/docs/chapter1/paragraph1/point2/","title":"Критерии подстановки","section":"Теория множеств","content":"Критерии подстановки#\rCS1#\rСравним операцию перехода от $\\boldsymbol{A}$ к $(\\boldsymbol{B}|\\boldsymbol{x})\\boldsymbol{A}$ с операцией перехода от $\\boldsymbol{A}$ к $(\\boldsymbol{B}|\\boldsymbol{x}^{\\prime})(\\boldsymbol{x}^{\\prime}|\\boldsymbol{x})\\boldsymbol{A}$.\nПри обеих операциях не изменяется ни один знак, содержащийся в $\\boldsymbol{A}$ и отличный от $\\boldsymbol{x}$. На каждое место, где $\\boldsymbol{x}$ встречается в $\\boldsymbol{A}$, мы должны подставить $\\boldsymbol{B}$ вместо $\\boldsymbol{x}$ как при первой, так и при второй операции: это очевидно для первой, а для второй это вытекает из того, что $\\boldsymbol{x}^{\\prime}$ не встречается в $\\boldsymbol{A}$.\nCS3#\rСравним операцию перехода от $\\boldsymbol{A}$ к $\\tau_{\\boldsymbol{x}}(\\boldsymbol{A})$ с операцией перехода от $\\boldsymbol{A}$ к $\\tau_{\\boldsymbol{x}^{\\prime}}(\\boldsymbol{A}^{\\prime})$, где $\\boldsymbol{A}^{\\prime}$ — знакосочетание $(\\boldsymbol{x}^{\\prime}|\\boldsymbol{x})\\boldsymbol{A}$.\nПри обеих операциях не изменяется ни один знак, содержащийся в $\\boldsymbol{A}$ и отличный от $\\boldsymbol{x}$, знак $\\tau$ добавится слева. Это очевидно для первой, а для второй это вытекает из того, что $\\boldsymbol{x}^{\\prime}$ не встречается в $\\boldsymbol{A}$.\nСоединяем связю каждый экземпляр буквы $\\boldsymbol{x}$ в $\\boldsymbol{A}$ со знаком $\\tau$, написанным слева от $\\boldsymbol{A}$, и заменяем букву $\\boldsymbol{x}$, каждый ее экземпляр, символом $\\square$, при обеих операциях.\nCS4#\rСравним операцию перехода от $\\boldsymbol{A}$ к $(\\boldsymbol{B}|\\boldsymbol{y})\\tau_{\\boldsymbol{x}}(\\boldsymbol{A})$ с операцией перехода от $\\boldsymbol{A}$ к $\\tau_{\\boldsymbol{x}}(\\boldsymbol{A}^{\\prime})$, где $\\boldsymbol{A}^{\\prime}$ — знакосочетание $(\\boldsymbol{B}|\\boldsymbol{y})\\boldsymbol{A}$.\nПри обеих операциях не изменяется ни один знак, содержащийся в $\\boldsymbol{A}$ и отличный от $\\boldsymbol{x}$ и $\\boldsymbol{y}$, знак $\\tau$ добавится слева.\nСоединяем связю каждый экземпляр буквы $\\boldsymbol{x}$ в $\\boldsymbol{A}$ со знаком $\\tau$, написанным слева от $\\boldsymbol{A}$, и заменяем букву $\\boldsymbol{x}$, каждый ее экземпляр, символом $\\square$, при обеих операциях.\nНаконец, на каждое место, где $\\boldsymbol{y}$ встречается в $\\boldsymbol{A}$, мы должны подставить $\\boldsymbol{B}$ вместо $\\boldsymbol{y}$ как при первой, так и при второй операции: это очевидно для первой, а для второй это вытекает из того, что $\\boldsymbol{x}$ не встречается в $\\boldsymbol{B}$.\nCS5#\rСравним операцию перехода от знакосочетаний $\\boldsymbol{A},\\boldsymbol{B}$ к $(\\boldsymbol{C}|\\boldsymbol{x})\\Rightarrow(\\boldsymbol{A}\\boldsymbol{B})$ с операцией перехода от знакосочетаний $\\boldsymbol{A},\\boldsymbol{B}$ к $\\Rightarrow \\boldsymbol{A}^{\\prime}\\boldsymbol{B}^{\\prime}$, где $\\boldsymbol{A}^{\\prime},\\boldsymbol{B}^{\\prime}$ суть соответственно $(\\boldsymbol{C}|\\boldsymbol{x})\\boldsymbol{A}$, $(\\boldsymbol{C}|\\boldsymbol{x})\\boldsymbol{B}$.\nПри обеих операциях не изменяется ни один знак, содержащийся в $\\boldsymbol{A}$ или $\\boldsymbol{B}$, и отличный от $\\boldsymbol{x}$, знакосочетание $\\vee\\lnot$ (изображаемое символом $\\Rightarrow$) добавится слева. На каждое место, где $\\boldsymbol{x}$ встречается в $\\boldsymbol{A}$ или $\\boldsymbol{B}$, мы должны подставить $\\boldsymbol{C}$ вместо $\\boldsymbol{x}$ при обеих операциях.\nАналогичным образом проверяется, что знакосочетания $(\\boldsymbol{C}|\\boldsymbol{x})(\\lnot\\boldsymbol{A})$, $(\\boldsymbol{C}|\\boldsymbol{x})(\\vee \\boldsymbol{A}\\boldsymbol{B})$, $(\\boldsymbol{C}|\\boldsymbol{x})(\\boldsymbol{s} \\boldsymbol{A}\\boldsymbol{B})$ ($\\boldsymbol{s}$ — специальный знак) тождественны соответственно с $\\lnot\\boldsymbol{A}^{\\prime}$, $\\vee \\boldsymbol{A}^{\\prime}\\boldsymbol{B}^{\\prime}$, $\\boldsymbol{s}\\boldsymbol{A}^{\\prime}\\boldsymbol{B}^{\\prime}$, где $\\boldsymbol{A}^{\\prime},\\boldsymbol{B}^{\\prime}$ суть соответственно $(\\boldsymbol{C}|\\boldsymbol{x})\\boldsymbol{A}$, $(\\boldsymbol{C}|\\boldsymbol{x})\\boldsymbol{B}$.\n"},{"id":1,"href":"/docs/","title":"Теория множеств","section":"Теория множеств","content":"Решения упражнений и примеров из книги «Теория множеств» Н. Бурбаки\n"}]